{
  "activity": [
  	{
  		"userImgURL": "icons/profile-pic-1.jpg",
  		"userName": "Tony Kobiashvili",
		"userAction": "commented on",
		"groupName": "YourApp's SEO Tips",
		"activityTime": "4 hours ago"
	},
	{
		"userImgURL": "icons/profile-pic-2.jpg",
  		"userName": "David Rios",
		"userAction": "liked the post",
		"groupName": "Facebook's Changed for 2016",
		"activityTime": "5 hours ago"
	},
		{
		"userImgURL": "icons/profile-pic-3.jpg",
  		"userName": "Mark Rubi",
		"userAction": "liked the post",
		"groupName": "Facebook's Changed for 2016",
		"activityTime": "5 hours ago"
	},
		{
		"userImgURL": "icons/profile-pic-4.jpg",
  		"userName": "Miguel Quito",
		"userAction": "posted",
		"groupName": "YourApp's SEO Tips",
		"activityTime": "1 day ago"
	}
  ]
}
